{
  "data_corrida": "2021-12-10",
  "corridas": [
    {
      "href_gh": "#result-meeting-result/race_id=1876166&track_id=76&r_date=2021-12-10&r_time=11:06"
    },
    {
      "href_gh": "#result-meeting-result/race_id=1876167&track_id=76&r_date=2021-12-10&r_time=11:21"
    },
    {
      "href_gh": "#result-meeting-result/race_id=1876168&track_id=76&r_date=2021-12-10&r_time=11:36"
    },
    {
      "href_gh": "#result-meeting-result/race_id=1876169&track_id=76&r_date=2021-12-10&r_time=11:51"
    },
    {
      "href_gh": "#result-meeting-result/race_id=1876170&track_id=76&r_date=2021-12-10&r_time=12:06"
    },
    {
      "href_gh": "#result-meeting-result/race_id=1876171&track_id=76&r_date=2021-12-10&r_time=12:21"
    },
    {
      "href_gh": "#result-meeting-result/race_id=1876172&track_id=76&r_date=2021-12-10&r_time=12:36"
    },
    {
      "href_gh": "#result-meeting-result/race_id=1876173&track_id=76&r_date=2021-12-10&r_time=12:51"
    },
    {
      "href_gh": "#result-meeting-result/race_id=1876174&track_id=76&r_date=2021-12-10&r_time=13:06"
    },
    {
      "href_gh": "#result-meeting-result/race_id=1876175&track_id=76&r_date=2021-12-10&r_time=13:21"
    },
    {
      "href_gh": "#result-meeting-result/race_id=1876176&track_id=76&r_date=2021-12-10&r_time=13:36"
    },
    {
      "href_gh": "#result-meeting-result/race_id=1876177&track_id=76&r_date=2021-12-10&r_time=13:51"
    },
    {
      "href_gh": "#result-meeting-result/race_id=1876192&track_id=39&r_date=2021-12-10&r_time=11:13"
    },
    {
      "href_gh": "#result-meeting-result/race_id=1876193&track_id=39&r_date=2021-12-10&r_time=11:28"
    },
    {
      "href_gh": "#result-meeting-result/race_id=1876194&track_id=39&r_date=2021-12-10&r_time=11:43"
    },
    {
      "href_gh": "#result-meeting-result/race_id=1876195&track_id=39&r_date=2021-12-10&r_time=11:58"
    },
    {
      "href_gh": "#result-meeting-result/race_id=1876196&track_id=39&r_date=2021-12-10&r_time=12:13"
    },
    {
      "href_gh": "#result-meeting-result/race_id=1876197&track_id=39&r_date=2021-12-10&r_time=12:28"
    },
    {
      "href_gh": "#result-meeting-result/race_id=1876198&track_id=39&r_date=2021-12-10&r_time=12:43"
    },
    {
      "href_gh": "#result-meeting-result/race_id=1876199&track_id=39&r_date=2021-12-10&r_time=12:58"
    },
    {
      "href_gh": "#result-meeting-result/race_id=1876200&track_id=39&r_date=2021-12-10&r_time=13:13"
    },
    {
      "href_gh": "#result-meeting-result/race_id=1876201&track_id=39&r_date=2021-12-10&r_time=13:28"
    },
    {
      "href_gh": "#result-meeting-result/race_id=1876202&track_id=39&r_date=2021-12-10&r_time=13:44"
    },
    {
      "href_gh": "#result-meeting-result/race_id=1876203&track_id=39&r_date=2021-12-10&r_time=13:59"
    },
    {
      "href_gh": "#result-meeting-result/race_id=1876301&track_id=6&r_date=2021-12-10&r_time=14:04"
    },
    {
      "href_gh": "#result-meeting-result/race_id=1876302&track_id=6&r_date=2021-12-10&r_time=14:19"
    },
    {
      "href_gh": "#result-meeting-result/race_id=1876303&track_id=6&r_date=2021-12-10&r_time=14:36"
    },
    {
      "href_gh": "#result-meeting-result/race_id=1876304&track_id=6&r_date=2021-12-10&r_time=14:54"
    },
    {
      "href_gh": "#result-meeting-result/race_id=1876305&track_id=6&r_date=2021-12-10&r_time=15:09"
    },
    {
      "href_gh": "#result-meeting-result/race_id=1876306&track_id=6&r_date=2021-12-10&r_time=15:26"
    },
    {
      "href_gh": "#result-meeting-result/race_id=1876307&track_id=6&r_date=2021-12-10&r_time=15:44"
    },
    {
      "href_gh": "#result-meeting-result/race_id=1876308&track_id=6&r_date=2021-12-10&r_time=16:04"
    },
    {
      "href_gh": "#result-meeting-result/race_id=1876309&track_id=6&r_date=2021-12-10&r_time=16:23"
    },
    {
      "href_gh": "#result-meeting-result/race_id=1876310&track_id=6&r_date=2021-12-10&r_time=16:43"
    },
    {
      "href_gh": "#result-meeting-result/race_id=1876311&track_id=6&r_date=2021-12-10&r_time=17:03"
    },
    {
      "href_gh": "#result-meeting-result/race_id=1876312&track_id=6&r_date=2021-12-10&r_time=17:22"
    },
    {
      "href_gh": "#result-meeting-result/race_id=1875672&track_id=33&r_date=2021-12-10&r_time=18:19"
    },
    {
      "href_gh": "#result-meeting-result/race_id=1875673&track_id=33&r_date=2021-12-10&r_time=18:36"
    },
    {
      "href_gh": "#result-meeting-result/race_id=1875674&track_id=33&r_date=2021-12-10&r_time=18:51"
    },
    {
      "href_gh": "#result-meeting-result/race_id=1875675&track_id=33&r_date=2021-12-10&r_time=19:09"
    },
    {
      "href_gh": "#result-meeting-result/race_id=1875676&track_id=33&r_date=2021-12-10&r_time=19:26"
    },
    {
      "href_gh": "#result-meeting-result/race_id=1875677&track_id=33&r_date=2021-12-10&r_time=19:41"
    },
    {
      "href_gh": "#result-meeting-result/race_id=1875678&track_id=33&r_date=2021-12-10&r_time=19:58"
    },
    {
      "href_gh": "#result-meeting-result/race_id=1875679&track_id=33&r_date=2021-12-10&r_time=20:12"
    },
    {
      "href_gh": "#result-meeting-result/race_id=1875680&track_id=33&r_date=2021-12-10&r_time=20:27"
    },
    {
      "href_gh": "#result-meeting-result/race_id=1875681&track_id=33&r_date=2021-12-10&r_time=20:46"
    },
    {
      "href_gh": "#result-meeting-result/race_id=1875682&track_id=33&r_date=2021-12-10&r_time=21:01"
    },
    {
      "href_gh": "#result-meeting-result/race_id=1875683&track_id=33&r_date=2021-12-10&r_time=21:16"
    },
    {
      "href_gh": "#result-meeting-result/race_id=1875684&track_id=33&r_date=2021-12-10&r_time=21:31"
    },
    {
      "href_gh": "#result-meeting-result/race_id=1875685&track_id=33&r_date=2021-12-10&r_time=21:48"
    },
    {
      "href_gh": "#result-meeting-result/race_id=1875897&track_id=98&r_date=2021-12-10&r_time=08:12"
    },
    {
      "href_gh": "#result-meeting-result/race_id=1875898&track_id=98&r_date=2021-12-10&r_time=08:27"
    },
    {
      "href_gh": "#result-meeting-result/race_id=1875899&track_id=98&r_date=2021-12-10&r_time=08:43"
    },
    {
      "href_gh": "#result-meeting-result/race_id=1875900&track_id=98&r_date=2021-12-10&r_time=09:02"
    },
    {
      "href_gh": "#result-meeting-result/race_id=1875901&track_id=98&r_date=2021-12-10&r_time=09:18"
    },
    {
      "href_gh": "#result-meeting-result/race_id=1875902&track_id=98&r_date=2021-12-10&r_time=09:34"
    },
    {
      "href_gh": "#result-meeting-result/race_id=1875903&track_id=98&r_date=2021-12-10&r_time=09:52"
    },
    {
      "href_gh": "#result-meeting-result/race_id=1875904&track_id=98&r_date=2021-12-10&r_time=10:07"
    },
    {
      "href_gh": "#result-meeting-result/race_id=1875905&track_id=98&r_date=2021-12-10&r_time=10:23"
    },
    {
      "href_gh": "#result-meeting-result/race_id=1875906&track_id=98&r_date=2021-12-10&r_time=10:41"
    },
    {
      "href_gh": "#result-meeting-result/race_id=1876031&track_id=69&r_date=2021-12-10&r_time=10:12"
    },
    {
      "href_gh": "#result-meeting-result/race_id=1876032&track_id=69&r_date=2021-12-10&r_time=10:31"
    },
    {
      "href_gh": "#result-meeting-result/race_id=1876033&track_id=69&r_date=2021-12-10&r_time=10:46"
    },
    {
      "href_gh": "#result-meeting-result/race_id=1876034&track_id=69&r_date=2021-12-10&r_time=11:01"
    },
    {
      "href_gh": "#result-meeting-result/race_id=1876035&track_id=69&r_date=2021-12-10&r_time=11:16"
    },
    {
      "href_gh": "#result-meeting-result/race_id=1876036&track_id=69&r_date=2021-12-10&r_time=11:31"
    },
    {
      "href_gh": "#result-meeting-result/race_id=1876037&track_id=69&r_date=2021-12-10&r_time=11:46"
    },
    {
      "href_gh": "#result-meeting-result/race_id=1876038&track_id=69&r_date=2021-12-10&r_time=12:01"
    },
    {
      "href_gh": "#result-meeting-result/race_id=1876039&track_id=69&r_date=2021-12-10&r_time=12:16"
    },
    {
      "href_gh": "#result-meeting-result/race_id=1876040&track_id=69&r_date=2021-12-10&r_time=12:31"
    },
    {
      "href_gh": "#result-meeting-result/race_id=1876041&track_id=69&r_date=2021-12-10&r_time=12:46"
    },
    {
      "href_gh": "#result-meeting-result/race_id=1876042&track_id=69&r_date=2021-12-10&r_time=13:02"
    },
    {
      "href_gh": "#result-meeting-result/race_id=1876043&track_id=69&r_date=2021-12-10&r_time=13:17"
    },
    {
      "href_gh": "#result-meeting-result/race_id=1876044&track_id=69&r_date=2021-12-10&r_time=13:33"
    },
    {
      "href_gh": "#result-meeting-result/race_id=1876093&track_id=5&r_date=2021-12-10&r_time=10:17"
    },
    {
      "href_gh": "#result-meeting-result/race_id=1876094&track_id=5&r_date=2021-12-10&r_time=10:37"
    },
    {
      "href_gh": "#result-meeting-result/race_id=1876095&track_id=5&r_date=2021-12-10&r_time=10:53"
    },
    {
      "href_gh": "#result-meeting-result/race_id=1876096&track_id=5&r_date=2021-12-10&r_time=11:09"
    },
    {
      "href_gh": "#result-meeting-result/race_id=1876097&track_id=5&r_date=2021-12-10&r_time=11:24"
    },
    {
      "href_gh": "#result-meeting-result/race_id=1876098&track_id=5&r_date=2021-12-10&r_time=11:39"
    },
    {
      "href_gh": "#result-meeting-result/race_id=1876099&track_id=5&r_date=2021-12-10&r_time=11:54"
    },
    {
      "href_gh": "#result-meeting-result/race_id=1876100&track_id=5&r_date=2021-12-10&r_time=12:09"
    },
    {
      "href_gh": "#result-meeting-result/race_id=1876101&track_id=5&r_date=2021-12-10&r_time=12:24"
    },
    {
      "href_gh": "#result-meeting-result/race_id=1876102&track_id=5&r_date=2021-12-10&r_time=12:39"
    },
    {
      "href_gh": "#result-meeting-result/race_id=1876103&track_id=5&r_date=2021-12-10&r_time=12:54"
    },
    {
      "href_gh": "#result-meeting-result/race_id=1876104&track_id=5&r_date=2021-12-10&r_time=13:09"
    },
    {
      "href_gh": "#result-meeting-result/race_id=1876105&track_id=5&r_date=2021-12-10&r_time=13:24"
    },
    {
      "href_gh": "#result-meeting-result/race_id=1876106&track_id=5&r_date=2021-12-10&r_time=13:39"
    },
    {
      "href_gh": "#result-meeting-result/race_id=1876107&track_id=1&r_date=2021-12-10&r_time=13:49"
    },
    {
      "href_gh": "#result-meeting-result/race_id=1876108&track_id=1&r_date=2021-12-10&r_time=14:07"
    },
    {
      "href_gh": "#result-meeting-result/race_id=1876109&track_id=1&r_date=2021-12-10&r_time=14:23"
    },
    {
      "href_gh": "#result-meeting-result/race_id=1876110&track_id=1&r_date=2021-12-10&r_time=14:42"
    },
    {
      "href_gh": "#result-meeting-result/race_id=1876111&track_id=1&r_date=2021-12-10&r_time=15:02"
    },
    {
      "href_gh": "#result-meeting-result/race_id=1876112&track_id=1&r_date=2021-12-10&r_time=15:18"
    },
    {
      "href_gh": "#result-meeting-result/race_id=1876113&track_id=1&r_date=2021-12-10&r_time=15:38"
    },
    {
      "href_gh": "#result-meeting-result/race_id=1876114&track_id=1&r_date=2021-12-10&r_time=15:58"
    },
    {
      "href_gh": "#result-meeting-result/race_id=1876115&track_id=1&r_date=2021-12-10&r_time=16:18"
    },
    {
      "href_gh": "#result-meeting-result/race_id=1876116&track_id=1&r_date=2021-12-10&r_time=16:38"
    },
    {
      "href_gh": "#result-meeting-result/race_id=1876117&track_id=1&r_date=2021-12-10&r_time=16:58"
    },
    {
      "href_gh": "#result-meeting-result/race_id=1876118&track_id=1&r_date=2021-12-10&r_time=17:18"
    },
    {
      "href_gh": "#result-meeting-result/race_id=1876119&track_id=1&r_date=2021-12-10&r_time=17:37"
    },
    {
      "href_gh": "#result-meeting-result/race_id=1876120&track_id=1&r_date=2021-12-10&r_time=17:54"
    },
    {
      "href_gh": "#result-meeting-result/race_id=1876263&track_id=4&r_date=2021-12-10&r_time=13:57"
    },
    {
      "href_gh": "#result-meeting-result/race_id=1876264&track_id=4&r_date=2021-12-10&r_time=14:12"
    },
    {
      "href_gh": "#result-meeting-result/race_id=1876265&track_id=4&r_date=2021-12-10&r_time=14:32"
    },
    {
      "href_gh": "#result-meeting-result/race_id=1876266&track_id=4&r_date=2021-12-10&r_time=14:52"
    },
    {
      "href_gh": "#result-meeting-result/race_id=1876267&track_id=4&r_date=2021-12-10&r_time=15:11"
    },
    {
      "href_gh": "#result-meeting-result/race_id=1876268&track_id=4&r_date=2021-12-10&r_time=15:28"
    },
    {
      "href_gh": "#result-meeting-result/race_id=1876269&track_id=4&r_date=2021-12-10&r_time=15:48"
    },
    {
      "href_gh": "#result-meeting-result/race_id=1876270&track_id=4&r_date=2021-12-10&r_time=16:08"
    },
    {
      "href_gh": "#result-meeting-result/race_id=1876271&track_id=4&r_date=2021-12-10&r_time=16:28"
    },
    {
      "href_gh": "#result-meeting-result/race_id=1876272&track_id=4&r_date=2021-12-10&r_time=16:48"
    },
    {
      "href_gh": "#result-meeting-result/race_id=1876273&track_id=4&r_date=2021-12-10&r_time=17:08"
    },
    {
      "href_gh": "#result-meeting-result/race_id=1876274&track_id=4&r_date=2021-12-10&r_time=17:28"
    },
    {
      "href_gh": "#result-meeting-result/race_id=1876275&track_id=4&r_date=2021-12-10&r_time=17:44"
    },
    {
      "href_gh": "#result-meeting-result/race_id=1876276&track_id=4&r_date=2021-12-10&r_time=18:02"
    },
    {
      "href_gh": "#result-meeting-result/race_id=1875907&track_id=11&r_date=2021-12-10&r_time=18:09"
    },
    {
      "href_gh": "#result-meeting-result/race_id=1875908&track_id=11&r_date=2021-12-10&r_time=18:28"
    },
    {
      "href_gh": "#result-meeting-result/race_id=1875909&track_id=11&r_date=2021-12-10&r_time=18:43"
    },
    {
      "href_gh": "#result-meeting-result/race_id=1875910&track_id=11&r_date=2021-12-10&r_time=18:58"
    },
    {
      "href_gh": "#result-meeting-result/race_id=1875911&track_id=11&r_date=2021-12-10&r_time=19:18"
    },
    {
      "href_gh": "#result-meeting-result/race_id=1875912&track_id=11&r_date=2021-12-10&r_time=19:36"
    },
    {
      "href_gh": "#result-meeting-result/race_id=1875913&track_id=11&r_date=2021-12-10&r_time=19:56"
    },
    {
      "href_gh": "#result-meeting-result/race_id=1875914&track_id=11&r_date=2021-12-10&r_time=20:17"
    },
    {
      "href_gh": "#result-meeting-result/race_id=1875915&track_id=11&r_date=2021-12-10&r_time=20:38"
    },
    {
      "href_gh": "#result-meeting-result/race_id=1875916&track_id=11&r_date=2021-12-10&r_time=20:54"
    },
    {
      "href_gh": "#result-meeting-result/race_id=1875917&track_id=11&r_date=2021-12-10&r_time=21:12"
    },
    {
      "href_gh": "#result-meeting-result/race_id=1875918&track_id=11&r_date=2021-12-10&r_time=21:28"
    },
    {
      "href_gh": "#result-meeting-result/race_id=1875919&track_id=11&r_date=2021-12-10&r_time=21:42"
    },
    {
      "href_gh": "#result-meeting-result/race_id=1876141&track_id=70&r_date=2021-12-10&r_time=18:17"
    },
    {
      "href_gh": "#result-meeting-result/race_id=1876142&track_id=70&r_date=2021-12-10&r_time=18:33"
    },
    {
      "href_gh": "#result-meeting-result/race_id=1876143&track_id=70&r_date=2021-12-10&r_time=18:48"
    },
    {
      "href_gh": "#result-meeting-result/race_id=1876144&track_id=70&r_date=2021-12-10&r_time=19:07"
    },
    {
      "href_gh": "#result-meeting-result/race_id=1876145&track_id=70&r_date=2021-12-10&r_time=19:24"
    },
    {
      "href_gh": "#result-meeting-result/race_id=1876146&track_id=70&r_date=2021-12-10&r_time=19:44"
    },
    {
      "href_gh": "#result-meeting-result/race_id=1876147&track_id=70&r_date=2021-12-10&r_time=20:03"
    },
    {
      "href_gh": "#result-meeting-result/race_id=1876148&track_id=70&r_date=2021-12-10&r_time=20:23"
    },
    {
      "href_gh": "#result-meeting-result/race_id=1876149&track_id=70&r_date=2021-12-10&r_time=20:43"
    },
    {
      "href_gh": "#result-meeting-result/race_id=1876150&track_id=70&r_date=2021-12-10&r_time=21:02"
    },
    {
      "href_gh": "#result-meeting-result/race_id=1876151&track_id=70&r_date=2021-12-10&r_time=21:18"
    },
    {
      "href_gh": "#result-meeting-result/race_id=1875931&track_id=42&r_date=2021-12-10&r_time=18:53"
    },
    {
      "href_gh": "#result-meeting-result/race_id=1875932&track_id=42&r_date=2021-12-10&r_time=19:12"
    },
    {
      "href_gh": "#result-meeting-result/race_id=1875933&track_id=42&r_date=2021-12-10&r_time=19:28"
    },
    {
      "href_gh": "#result-meeting-result/race_id=1875934&track_id=42&r_date=2021-12-10&r_time=19:42"
    },
    {
      "href_gh": "#result-meeting-result/race_id=1875935&track_id=42&r_date=2021-12-10&r_time=19:54"
    },
    {
      "href_gh": "#result-meeting-result/race_id=1875936&track_id=42&r_date=2021-12-10&r_time=20:09"
    },
    {
      "href_gh": "#result-meeting-result/race_id=1875937&track_id=42&r_date=2021-12-10&r_time=20:29"
    },
    {
      "href_gh": "#result-meeting-result/race_id=1875938&track_id=42&r_date=2021-12-10&r_time=20:47"
    },
    {
      "href_gh": "#result-meeting-result/race_id=1875939&track_id=42&r_date=2021-12-10&r_time=21:06"
    },
    {
      "href_gh": "#result-meeting-result/race_id=1875940&track_id=42&r_date=2021-12-10&r_time=21:22"
    },
    {
      "href_gh": "#result-meeting-result/race_id=1876239&track_id=34&r_date=2021-12-10&r_time=19:34"
    },
    {
      "href_gh": "#result-meeting-result/race_id=1876240&track_id=34&r_date=2021-12-10&r_time=19:51"
    },
    {
      "href_gh": "#result-meeting-result/race_id=1876241&track_id=34&r_date=2021-12-10&r_time=20:08"
    },
    {
      "href_gh": "#result-meeting-result/race_id=1876242&track_id=34&r_date=2021-12-10&r_time=20:25"
    },
    {
      "href_gh": "#result-meeting-result/race_id=1876243&track_id=34&r_date=2021-12-10&r_time=20:42"
    },
    {
      "href_gh": "#result-meeting-result/race_id=1876244&track_id=34&r_date=2021-12-10&r_time=20:59"
    },
    {
      "href_gh": "#result-meeting-result/race_id=1876245&track_id=34&r_date=2021-12-10&r_time=21:16"
    },
    {
      "href_gh": "#result-meeting-result/race_id=1876246&track_id=34&r_date=2021-12-10&r_time=21:33"
    },
    {
      "href_gh": "#result-meeting-result/race_id=1876247&track_id=34&r_date=2021-12-10&r_time=21:50"
    },
    {
      "href_gh": "#result-meeting-result/race_id=1876248&track_id=34&r_date=2021-12-10&r_time=22:07"
    },
    {
      "href_gh": "#result-meeting-result/race_id=1875920&track_id=41&r_date=2021-12-10&r_time=19:25"
    },
    {
      "href_gh": "#result-meeting-result/race_id=1875921&track_id=41&r_date=2021-12-10&r_time=19:42"
    },
    {
      "href_gh": "#result-meeting-result/race_id=1875922&track_id=41&r_date=2021-12-10&r_time=19:54"
    },
    {
      "href_gh": "#result-meeting-result/race_id=1875923&track_id=41&r_date=2021-12-10&r_time=20:09"
    },
    {
      "href_gh": "#result-meeting-result/race_id=1875924&track_id=41&r_date=2021-12-10&r_time=20:21"
    },
    {
      "href_gh": "#result-meeting-result/race_id=1875925&track_id=41&r_date=2021-12-10&r_time=20:33"
    },
    {
      "href_gh": "#result-meeting-result/race_id=1875926&track_id=41&r_date=2021-12-10&r_time=20:48"
    },
    {
      "href_gh": "#result-meeting-result/race_id=1875927&track_id=41&r_date=2021-12-10&r_time=21:00"
    },
    {
      "href_gh": "#result-meeting-result/race_id=1875928&track_id=41&r_date=2021-12-10&r_time=21:15"
    },
    {
      "href_gh": "#result-meeting-result/race_id=1875929&track_id=41&r_date=2021-12-10&r_time=21:27"
    },
    {
      "href_gh": "#result-meeting-result/race_id=1875963&track_id=50&r_date=2021-12-10&r_time=19:30"
    },
    {
      "href_gh": "#result-meeting-result/race_id=1875964&track_id=50&r_date=2021-12-10&r_time=19:42"
    },
    {
      "href_gh": "#result-meeting-result/race_id=1875965&track_id=50&r_date=2021-12-10&r_time=19:57"
    },
    {
      "href_gh": "#result-meeting-result/race_id=1875966&track_id=50&r_date=2021-12-10&r_time=20:09"
    },
    {
      "href_gh": "#result-meeting-result/race_id=1875967&track_id=50&r_date=2021-12-10&r_time=20:24"
    },
    {
      "href_gh": "#result-meeting-result/race_id=1875968&track_id=50&r_date=2021-12-10&r_time=20:36"
    },
    {
      "href_gh": "#result-meeting-result/race_id=1875969&track_id=50&r_date=2021-12-10&r_time=20:51"
    },
    {
      "href_gh": "#result-meeting-result/race_id=1875970&track_id=50&r_date=2021-12-10&r_time=21:03"
    },
    {
      "href_gh": "#result-meeting-result/race_id=1875971&track_id=50&r_date=2021-12-10&r_time=21:18"
    },
    {
      "href_gh": "#result-meeting-result/race_id=1875972&track_id=50&r_date=2021-12-10&r_time=21:30"
    },
    {
      "href_gh": "#result-meeting-result/race_id=1875974&track_id=40&r_date=2021-12-10&r_time=19:39"
    },
    {
      "href_gh": "#result-meeting-result/race_id=1875975&track_id=40&r_date=2021-12-10&r_time=19:54"
    },
    {
      "href_gh": "#result-meeting-result/race_id=1875976&track_id=40&r_date=2021-12-10&r_time=20:09"
    },
    {
      "href_gh": "#result-meeting-result/race_id=1875977&track_id=40&r_date=2021-12-10&r_time=20:24"
    },
    {
      "href_gh": "#result-meeting-result/race_id=1875978&track_id=40&r_date=2021-12-10&r_time=20:39"
    },
    {
      "href_gh": "#result-meeting-result/race_id=1875979&track_id=40&r_date=2021-12-10&r_time=20:54"
    },
    {
      "href_gh": "#result-meeting-result/race_id=1875980&track_id=40&r_date=2021-12-10&r_time=21:09"
    },
    {
      "href_gh": "#result-meeting-result/race_id=1875981&track_id=40&r_date=2021-12-10&r_time=21:24"
    },
    {
      "href_gh": "#result-meeting-result/race_id=1875982&track_id=40&r_date=2021-12-10&r_time=21:39"
    },
    {
      "href_gh": "#result-meeting-result/race_id=1875983&track_id=40&r_date=2021-12-10&r_time=21:54"
    },
    {
      "href_gh": "#result-meeting-result/race_id=1875984&track_id=40&r_date=2021-12-10&r_time=22:09"
    },
    {
      "href_gh": "#result-meeting-result/race_id=1875357&track_id=21&r_date=2021-12-10&r_time=19:42"
    },
    {
      "href_gh": "#result-meeting-result/race_id=1876346&track_id=21&r_date=2021-12-10&r_time=19:57"
    },
    {
      "href_gh": "#result-meeting-result/race_id=1876347&track_id=21&r_date=2021-12-10&r_time=20:12"
    },
    {
      "href_gh": "#result-meeting-result/race_id=1876348&track_id=21&r_date=2021-12-10&r_time=20:27"
    },
    {
      "href_gh": "#result-meeting-result/race_id=1876349&track_id=21&r_date=2021-12-10&r_time=20:42"
    },
    {
      "href_gh": "#result-meeting-result/race_id=1876350&track_id=21&r_date=2021-12-10&r_time=20:57"
    },
    {
      "href_gh": "#result-meeting-result/race_id=1876351&track_id=21&r_date=2021-12-10&r_time=21:12"
    },
    {
      "href_gh": "#result-meeting-result/race_id=1876352&track_id=21&r_date=2021-12-10&r_time=21:27"
    },
    {
      "href_gh": "#result-meeting-result/race_id=1876353&track_id=21&r_date=2021-12-10&r_time=21:42"
    },
    {
      "href_gh": "#result-meeting-result/race_id=1876354&track_id=21&r_date=2021-12-10&r_time=21:57"
    },
    {
      "href_gh": "#result-meeting-result/race_id=1876152&track_id=57&r_date=2021-12-10&r_time=19:46"
    },
    {
      "href_gh": "#result-meeting-result/race_id=1876153&track_id=57&r_date=2021-12-10&r_time=20:01"
    },
    {
      "href_gh": "#result-meeting-result/race_id=1876154&track_id=57&r_date=2021-12-10&r_time=20:16"
    },
    {
      "href_gh": "#result-meeting-result/race_id=1876155&track_id=57&r_date=2021-12-10&r_time=20:31"
    },
    {
      "href_gh": "#result-meeting-result/race_id=1876156&track_id=57&r_date=2021-12-10&r_time=20:46"
    },
    {
      "href_gh": "#result-meeting-result/race_id=1876157&track_id=57&r_date=2021-12-10&r_time=21:01"
    },
    {
      "href_gh": "#result-meeting-result/race_id=1876158&track_id=57&r_date=2021-12-10&r_time=21:16"
    },
    {
      "href_gh": "#result-meeting-result/race_id=1876159&track_id=57&r_date=2021-12-10&r_time=21:31"
    },
    {
      "href_gh": "#result-meeting-result/race_id=1876160&track_id=57&r_date=2021-12-10&r_time=21:46"
    },
    {
      "href_gh": "#result-meeting-result/race_id=1876161&track_id=57&r_date=2021-12-10&r_time=22:01"
    },
    {
      "href_gh": "#result-meeting-result/race_id=1875943&track_id=45&r_date=2021-12-10&r_time=19:50"
    },
    {
      "href_gh": "#result-meeting-result/race_id=1875944&track_id=45&r_date=2021-12-10&r_time=20:02"
    },
    {
      "href_gh": "#result-meeting-result/race_id=1875945&track_id=45&r_date=2021-12-10&r_time=20:14"
    },
    {
      "href_gh": "#result-meeting-result/race_id=1875946&track_id=45&r_date=2021-12-10&r_time=20:26"
    },
    {
      "href_gh": "#result-meeting-result/race_id=1875947&track_id=45&r_date=2021-12-10&r_time=20:38"
    },
    {
      "href_gh": "#result-meeting-result/race_id=1875948&track_id=45&r_date=2021-12-10&r_time=20:50"
    },
    {
      "href_gh": "#result-meeting-result/race_id=1875949&track_id=45&r_date=2021-12-10&r_time=21:02"
    },
    {
      "href_gh": "#result-meeting-result/race_id=1875950&track_id=45&r_date=2021-12-10&r_time=21:14"
    },
    {
      "href_gh": "#result-meeting-result/race_id=1875951&track_id=45&r_date=2021-12-10&r_time=21:26"
    },
    {
      "href_gh": "#result-meeting-result/race_id=1875952&track_id=49&r_date=2021-12-10&r_time=19:52"
    },
    {
      "href_gh": "#result-meeting-result/race_id=1875953&track_id=49&r_date=2021-12-10&r_time=20:07"
    },
    {
      "href_gh": "#result-meeting-result/race_id=1875954&track_id=49&r_date=2021-12-10&r_time=20:22"
    },
    {
      "href_gh": "#result-meeting-result/race_id=1875955&track_id=49&r_date=2021-12-10&r_time=20:37"
    },
    {
      "href_gh": "#result-meeting-result/race_id=1875956&track_id=49&r_date=2021-12-10&r_time=20:52"
    },
    {
      "href_gh": "#result-meeting-result/race_id=1875957&track_id=49&r_date=2021-12-10&r_time=21:07"
    },
    {
      "href_gh": "#result-meeting-result/race_id=1875958&track_id=49&r_date=2021-12-10&r_time=21:22"
    },
    {
      "href_gh": "#result-meeting-result/race_id=1875959&track_id=49&r_date=2021-12-10&r_time=21:37"
    },
    {
      "href_gh": "#result-meeting-result/race_id=1875960&track_id=49&r_date=2021-12-10&r_time=21:52"
    },
    {
      "href_gh": "#result-meeting-result/race_id=1875961&track_id=49&r_date=2021-12-10&r_time=22:07"
    },
    {
      "href_gh": "#result-meeting-result/race_id=1876335&track_id=55&r_date=2021-12-10&r_time=20:00"
    },
    {
      "href_gh": "#result-meeting-result/race_id=1876336&track_id=55&r_date=2021-12-10&r_time=20:15"
    },
    {
      "href_gh": "#result-meeting-result/race_id=1876337&track_id=55&r_date=2021-12-10&r_time=20:30"
    },
    {
      "href_gh": "#result-meeting-result/race_id=1876338&track_id=55&r_date=2021-12-10&r_time=20:45"
    },
    {
      "href_gh": "#result-meeting-result/race_id=1876339&track_id=55&r_date=2021-12-10&r_time=21:00"
    },
    {
      "href_gh": "#result-meeting-result/race_id=1876340&track_id=55&r_date=2021-12-10&r_time=21:15"
    },
    {
      "href_gh": "#result-meeting-result/race_id=1876341&track_id=55&r_date=2021-12-10&r_time=21:30"
    },
    {
      "href_gh": "#result-meeting-result/race_id=1876342&track_id=55&r_date=2021-12-10&r_time=21:45"
    },
    {
      "href_gh": "#result-meeting-result/race_id=1876343&track_id=55&r_date=2021-12-10&r_time=22:00"
    },
    {
      "href_gh": "#result-meeting-result/race_id=1876344&track_id=55&r_date=2021-12-10&r_time=22:15"
    },
    {
      "href_gh": "#result-meeting-result/race_id=1876345&track_id=55&r_date=2021-12-10&r_time=22:30"
    },
    {
      "href_gh": "#result-meeting-result/race_id=1876325&track_id=88&r_date=2021-12-10&r_time=20:05"
    },
    {
      "href_gh": "#result-meeting-result/race_id=1876326&track_id=88&r_date=2021-12-10&r_time=20:20"
    },
    {
      "href_gh": "#result-meeting-result/race_id=1876327&track_id=88&r_date=2021-12-10&r_time=20:35"
    },
    {
      "href_gh": "#result-meeting-result/race_id=1876328&track_id=88&r_date=2021-12-10&r_time=20:50"
    },
    {
      "href_gh": "#result-meeting-result/race_id=1876329&track_id=88&r_date=2021-12-10&r_time=21:05"
    },
    {
      "href_gh": "#result-meeting-result/race_id=1876330&track_id=88&r_date=2021-12-10&r_time=21:20"
    },
    {
      "href_gh": "#result-meeting-result/race_id=1876331&track_id=88&r_date=2021-12-10&r_time=21:35"
    },
    {
      "href_gh": "#result-meeting-result/race_id=1876332&track_id=88&r_date=2021-12-10&r_time=21:50"
    },
    {
      "href_gh": "#result-meeting-result/race_id=1876333&track_id=88&r_date=2021-12-10&r_time=22:05"
    },
    {
      "href_gh": "#result-meeting-result/race_id=1875941&track_id=42&r_date=2021-12-10&r_time=21:36"
    }
  ]
}