{
  "data_corrida": "2025-09-15",
  "corridas": [
    {
      "href_gh": "#result-meeting-result/race_id=2154767&track_id=99&r_date=2025-09-15&r_time=11:03"
    },
    {
      "href_gh": "#result-meeting-result/race_id=2154768&track_id=99&r_date=2025-09-15&r_time=11:19"
    },
    {
      "href_gh": "#result-meeting-result/race_id=2154769&track_id=99&r_date=2025-09-15&r_time=11:36"
    },
    {
      "href_gh": "#result-meeting-result/race_id=2154770&track_id=99&r_date=2025-09-15&r_time=11:52"
    },
    {
      "href_gh": "#result-meeting-result/race_id=2154771&track_id=99&r_date=2025-09-15&r_time=12:09"
    },
    {
      "href_gh": "#result-meeting-result/race_id=2154772&track_id=99&r_date=2025-09-15&r_time=12:26"
    },
    {
      "href_gh": "#result-meeting-result/race_id=2154773&track_id=99&r_date=2025-09-15&r_time=12:42"
    },
    {
      "href_gh": "#result-meeting-result/race_id=2154774&track_id=99&r_date=2025-09-15&r_time=12:59"
    },
    {
      "href_gh": "#result-meeting-result/race_id=2154775&track_id=99&r_date=2025-09-15&r_time=13:16"
    },
    {
      "href_gh": "#result-meeting-result/race_id=2154776&track_id=99&r_date=2025-09-15&r_time=13:31"
    },
    {
      "href_gh": "#result-meeting-result/race_id=2154889&track_id=11&r_date=2025-09-15&r_time=11:09"
    },
    {
      "href_gh": "#result-meeting-result/race_id=2154890&track_id=11&r_date=2025-09-15&r_time=11:26"
    },
    {
      "href_gh": "#result-meeting-result/race_id=2154891&track_id=11&r_date=2025-09-15&r_time=11:42"
    },
    {
      "href_gh": "#result-meeting-result/race_id=2154892&track_id=11&r_date=2025-09-15&r_time=11:58"
    },
    {
      "href_gh": "#result-meeting-result/race_id=2154893&track_id=11&r_date=2025-09-15&r_time=12:14"
    },
    {
      "href_gh": "#result-meeting-result/race_id=2154894&track_id=11&r_date=2025-09-15&r_time=12:31"
    },
    {
      "href_gh": "#result-meeting-result/race_id=2154895&track_id=11&r_date=2025-09-15&r_time=12:49"
    },
    {
      "href_gh": "#result-meeting-result/race_id=2154896&track_id=11&r_date=2025-09-15&r_time=13:06"
    },
    {
      "href_gh": "#result-meeting-result/race_id=2154897&track_id=11&r_date=2025-09-15&r_time=13:21"
    },
    {
      "href_gh": "#result-meeting-result/race_id=2154898&track_id=11&r_date=2025-09-15&r_time=13:36"
    },
    {
      "href_gh": "#result-meeting-result/race_id=2154899&track_id=11&r_date=2025-09-15&r_time=13:52"
    },
    {
      "href_gh": "#result-meeting-result/race_id=2154900&track_id=11&r_date=2025-09-15&r_time=14:09"
    },
    {
      "href_gh": "#result-meeting-result/race_id=2154777&track_id=39&r_date=2025-09-15&r_time=11:31"
    },
    {
      "href_gh": "#result-meeting-result/race_id=2154778&track_id=39&r_date=2025-09-15&r_time=11:47"
    },
    {
      "href_gh": "#result-meeting-result/race_id=2154779&track_id=39&r_date=2025-09-15&r_time=12:04"
    },
    {
      "href_gh": "#result-meeting-result/race_id=2154780&track_id=39&r_date=2025-09-15&r_time=12:21"
    },
    {
      "href_gh": "#result-meeting-result/race_id=2154781&track_id=39&r_date=2025-09-15&r_time=12:37"
    },
    {
      "href_gh": "#result-meeting-result/race_id=2154782&track_id=39&r_date=2025-09-15&r_time=12:54"
    },
    {
      "href_gh": "#result-meeting-result/race_id=2154783&track_id=39&r_date=2025-09-15&r_time=13:11"
    },
    {
      "href_gh": "#result-meeting-result/race_id=2154784&track_id=39&r_date=2025-09-15&r_time=13:26"
    },
    {
      "href_gh": "#result-meeting-result/race_id=2154785&track_id=39&r_date=2025-09-15&r_time=13:41"
    },
    {
      "href_gh": "#result-meeting-result/race_id=2154786&track_id=39&r_date=2025-09-15&r_time=13:58"
    },
    {
      "href_gh": "#result-meeting-result/race_id=2154839&track_id=4&r_date=2025-09-15&r_time=14:23"
    },
    {
      "href_gh": "#result-meeting-result/race_id=2154840&track_id=4&r_date=2025-09-15&r_time=14:41"
    },
    {
      "href_gh": "#result-meeting-result/race_id=2154841&track_id=4&r_date=2025-09-15&r_time=15:01"
    },
    {
      "href_gh": "#result-meeting-result/race_id=2154842&track_id=4&r_date=2025-09-15&r_time=15:19"
    },
    {
      "href_gh": "#result-meeting-result/race_id=2154843&track_id=4&r_date=2025-09-15&r_time=15:38"
    },
    {
      "href_gh": "#result-meeting-result/race_id=2154844&track_id=4&r_date=2025-09-15&r_time=15:57"
    },
    {
      "href_gh": "#result-meeting-result/race_id=2154845&track_id=4&r_date=2025-09-15&r_time=16:16"
    },
    {
      "href_gh": "#result-meeting-result/race_id=2154846&track_id=4&r_date=2025-09-15&r_time=16:34"
    },
    {
      "href_gh": "#result-meeting-result/race_id=2154847&track_id=4&r_date=2025-09-15&r_time=16:53"
    },
    {
      "href_gh": "#result-meeting-result/race_id=2154848&track_id=4&r_date=2025-09-15&r_time=17:12"
    },
    {
      "href_gh": "#result-meeting-result/race_id=2154849&track_id=4&r_date=2025-09-15&r_time=17:31"
    },
    {
      "href_gh": "#result-meeting-result/race_id=2154850&track_id=4&r_date=2025-09-15&r_time=17:49"
    },
    {
      "href_gh": "#result-meeting-result/race_id=2154901&track_id=61&r_date=2025-09-15&r_time=14:29"
    },
    {
      "href_gh": "#result-meeting-result/race_id=2154902&track_id=61&r_date=2025-09-15&r_time=14:48"
    },
    {
      "href_gh": "#result-meeting-result/race_id=2154903&track_id=61&r_date=2025-09-15&r_time=15:07"
    },
    {
      "href_gh": "#result-meeting-result/race_id=2154904&track_id=61&r_date=2025-09-15&r_time=15:26"
    },
    {
      "href_gh": "#result-meeting-result/race_id=2154905&track_id=61&r_date=2025-09-15&r_time=15:44"
    },
    {
      "href_gh": "#result-meeting-result/race_id=2154906&track_id=61&r_date=2025-09-15&r_time=16:03"
    },
    {
      "href_gh": "#result-meeting-result/race_id=2154907&track_id=61&r_date=2025-09-15&r_time=16:22"
    },
    {
      "href_gh": "#result-meeting-result/race_id=2154908&track_id=61&r_date=2025-09-15&r_time=16:41"
    },
    {
      "href_gh": "#result-meeting-result/race_id=2154909&track_id=61&r_date=2025-09-15&r_time=16:59"
    },
    {
      "href_gh": "#result-meeting-result/race_id=2154910&track_id=61&r_date=2025-09-15&r_time=17:18"
    },
    {
      "href_gh": "#result-meeting-result/race_id=2154911&track_id=61&r_date=2025-09-15&r_time=17:37"
    },
    {
      "href_gh": "#result-meeting-result/race_id=2154912&track_id=61&r_date=2025-09-15&r_time=17:56"
    },
    {
      "href_gh": "#result-meeting-result/race_id=2154787&track_id=70&r_date=2025-09-15&r_time=14:54"
    },
    {
      "href_gh": "#result-meeting-result/race_id=2154788&track_id=70&r_date=2025-09-15&r_time=15:13"
    },
    {
      "href_gh": "#result-meeting-result/race_id=2154789&track_id=70&r_date=2025-09-15&r_time=15:32"
    },
    {
      "href_gh": "#result-meeting-result/race_id=2154790&track_id=70&r_date=2025-09-15&r_time=15:51"
    },
    {
      "href_gh": "#result-meeting-result/race_id=2154791&track_id=70&r_date=2025-09-15&r_time=16:09"
    },
    {
      "href_gh": "#result-meeting-result/race_id=2154792&track_id=70&r_date=2025-09-15&r_time=16:28"
    },
    {
      "href_gh": "#result-meeting-result/race_id=2154793&track_id=70&r_date=2025-09-15&r_time=16:47"
    },
    {
      "href_gh": "#result-meeting-result/race_id=2154794&track_id=70&r_date=2025-09-15&r_time=17:06"
    },
    {
      "href_gh": "#result-meeting-result/race_id=2154795&track_id=70&r_date=2025-09-15&r_time=17:24"
    },
    {
      "href_gh": "#result-meeting-result/race_id=2154796&track_id=70&r_date=2025-09-15&r_time=17:43"
    },
    {
      "href_gh": "#result-meeting-result/race_id=2154797&track_id=76&r_date=2025-09-15&r_time=18:08"
    },
    {
      "href_gh": "#result-meeting-result/race_id=2154798&track_id=76&r_date=2025-09-15&r_time=18:26"
    },
    {
      "href_gh": "#result-meeting-result/race_id=2154799&track_id=76&r_date=2025-09-15&r_time=18:42"
    },
    {
      "href_gh": "#result-meeting-result/race_id=2154800&track_id=76&r_date=2025-09-15&r_time=18:59"
    },
    {
      "href_gh": "#result-meeting-result/race_id=2154801&track_id=76&r_date=2025-09-15&r_time=19:16"
    },
    {
      "href_gh": "#result-meeting-result/race_id=2154802&track_id=76&r_date=2025-09-15&r_time=19:33"
    },
    {
      "href_gh": "#result-meeting-result/race_id=2154803&track_id=76&r_date=2025-09-15&r_time=19:49"
    },
    {
      "href_gh": "#result-meeting-result/race_id=2154804&track_id=76&r_date=2025-09-15&r_time=20:07"
    },
    {
      "href_gh": "#result-meeting-result/race_id=2154805&track_id=76&r_date=2025-09-15&r_time=20:24"
    },
    {
      "href_gh": "#result-meeting-result/race_id=2154806&track_id=76&r_date=2025-09-15&r_time=20:41"
    },
    {
      "href_gh": "#result-meeting-result/race_id=2154807&track_id=76&r_date=2025-09-15&r_time=20:59"
    },
    {
      "href_gh": "#result-meeting-result/race_id=2154808&track_id=76&r_date=2025-09-15&r_time=21:16"
    },
    {
      "href_gh": "#result-meeting-result/race_id=2154736&track_id=16&r_date=2025-09-15&r_time=18:14"
    },
    {
      "href_gh": "#result-meeting-result/race_id=2154737&track_id=16&r_date=2025-09-15&r_time=18:31"
    },
    {
      "href_gh": "#result-meeting-result/race_id=2154738&track_id=16&r_date=2025-09-15&r_time=18:48"
    },
    {
      "href_gh": "#result-meeting-result/race_id=2154739&track_id=16&r_date=2025-09-15&r_time=19:06"
    },
    {
      "href_gh": "#result-meeting-result/race_id=2154740&track_id=16&r_date=2025-09-15&r_time=19:22"
    },
    {
      "href_gh": "#result-meeting-result/race_id=2154741&track_id=16&r_date=2025-09-15&r_time=19:39"
    },
    {
      "href_gh": "#result-meeting-result/race_id=2154742&track_id=16&r_date=2025-09-15&r_time=19:56"
    },
    {
      "href_gh": "#result-meeting-result/race_id=2154743&track_id=16&r_date=2025-09-15&r_time=20:13"
    },
    {
      "href_gh": "#result-meeting-result/race_id=2154744&track_id=16&r_date=2025-09-15&r_time=20:31"
    },
    {
      "href_gh": "#result-meeting-result/race_id=2154745&track_id=16&r_date=2025-09-15&r_time=20:47"
    },
    {
      "href_gh": "#result-meeting-result/race_id=2154746&track_id=16&r_date=2025-09-15&r_time=21:04"
    },
    {
      "href_gh": "#result-meeting-result/race_id=2154747&track_id=16&r_date=2025-09-15&r_time=21:23"
    },
    {
      "href_gh": "#result-meeting-result/race_id=2154809&track_id=33&r_date=2025-09-15&r_time=18:37"
    },
    {
      "href_gh": "#result-meeting-result/race_id=2154810&track_id=33&r_date=2025-09-15&r_time=18:53"
    },
    {
      "href_gh": "#result-meeting-result/race_id=2154811&track_id=33&r_date=2025-09-15&r_time=19:11"
    },
    {
      "href_gh": "#result-meeting-result/race_id=2154812&track_id=33&r_date=2025-09-15&r_time=19:27"
    },
    {
      "href_gh": "#result-meeting-result/race_id=2154813&track_id=33&r_date=2025-09-15&r_time=19:44"
    },
    {
      "href_gh": "#result-meeting-result/race_id=2154814&track_id=33&r_date=2025-09-15&r_time=20:01"
    },
    {
      "href_gh": "#result-meeting-result/race_id=2154815&track_id=33&r_date=2025-09-15&r_time=20:19"
    },
    {
      "href_gh": "#result-meeting-result/race_id=2154816&track_id=33&r_date=2025-09-15&r_time=20:36"
    },
    {
      "href_gh": "#result-meeting-result/race_id=2154817&track_id=33&r_date=2025-09-15&r_time=20:54"
    },
    {
      "href_gh": "#result-meeting-result/race_id=2154818&track_id=33&r_date=2025-09-15&r_time=21:11"
    },
    {
      "href_gh": "#result-meeting-result/race_id=2154819&track_id=33&r_date=2025-09-15&r_time=21:28"
    },
    {
      "href_gh": "#result-meeting-result/race_id=2154820&track_id=33&r_date=2025-09-15&r_time=21:46"
    },
    {
      "href_gh": "#result-meeting-result/race_id=2154714&track_id=69&r_date=2025-09-15&r_time=10:32"
    },
    {
      "href_gh": "#result-meeting-result/race_id=2154715&track_id=69&r_date=2025-09-15&r_time=10:48"
    },
    {
      "href_gh": "#result-meeting-result/race_id=2154716&track_id=69&r_date=2025-09-15&r_time=11:04"
    },
    {
      "href_gh": "#result-meeting-result/race_id=2154717&track_id=69&r_date=2025-09-15&r_time=11:21"
    },
    {
      "href_gh": "#result-meeting-result/race_id=2154718&track_id=69&r_date=2025-09-15&r_time=11:38"
    },
    {
      "href_gh": "#result-meeting-result/race_id=2154719&track_id=69&r_date=2025-09-15&r_time=11:54"
    },
    {
      "href_gh": "#result-meeting-result/race_id=2154720&track_id=69&r_date=2025-09-15&r_time=12:12"
    },
    {
      "href_gh": "#result-meeting-result/race_id=2154721&track_id=69&r_date=2025-09-15&r_time=12:29"
    },
    {
      "href_gh": "#result-meeting-result/race_id=2154722&track_id=69&r_date=2025-09-15&r_time=12:46"
    },
    {
      "href_gh": "#result-meeting-result/race_id=2154723&track_id=69&r_date=2025-09-15&r_time=13:03"
    },
    {
      "href_gh": "#result-meeting-result/race_id=2154724&track_id=69&r_date=2025-09-15&r_time=13:19"
    },
    {
      "href_gh": "#result-meeting-result/race_id=2154725&track_id=69&r_date=2025-09-15&r_time=13:37"
    },
    {
      "href_gh": "#result-meeting-result/race_id=2154696&track_id=59&r_date=2025-09-15&r_time=11:13"
    },
    {
      "href_gh": "#result-meeting-result/race_id=2154697&track_id=59&r_date=2025-09-15&r_time=11:29"
    },
    {
      "href_gh": "#result-meeting-result/race_id=2154698&track_id=59&r_date=2025-09-15&r_time=11:47"
    },
    {
      "href_gh": "#result-meeting-result/race_id=2154699&track_id=59&r_date=2025-09-15&r_time=12:04"
    },
    {
      "href_gh": "#result-meeting-result/race_id=2154700&track_id=59&r_date=2025-09-15&r_time=12:21"
    },
    {
      "href_gh": "#result-meeting-result/race_id=2154701&track_id=59&r_date=2025-09-15&r_time=12:38"
    },
    {
      "href_gh": "#result-meeting-result/race_id=2154702&track_id=59&r_date=2025-09-15&r_time=12:54"
    },
    {
      "href_gh": "#result-meeting-result/race_id=2154703&track_id=59&r_date=2025-09-15&r_time=13:12"
    },
    {
      "href_gh": "#result-meeting-result/race_id=2154704&track_id=59&r_date=2025-09-15&r_time=13:29"
    },
    {
      "href_gh": "#result-meeting-result/race_id=2154705&track_id=59&r_date=2025-09-15&r_time=13:47"
    },
    {
      "href_gh": "#result-meeting-result/race_id=2154706&track_id=59&r_date=2025-09-15&r_time=14:03"
    },
    {
      "href_gh": "#result-meeting-result/race_id=2154821&track_id=7&r_date=2025-09-15&r_time=14:26"
    },
    {
      "href_gh": "#result-meeting-result/race_id=2154822&track_id=7&r_date=2025-09-15&r_time=14:44"
    },
    {
      "href_gh": "#result-meeting-result/race_id=2154823&track_id=7&r_date=2025-09-15&r_time=15:03"
    },
    {
      "href_gh": "#result-meeting-result/race_id=2154824&track_id=7&r_date=2025-09-15&r_time=15:22"
    },
    {
      "href_gh": "#result-meeting-result/race_id=2154825&track_id=7&r_date=2025-09-15&r_time=15:41"
    },
    {
      "href_gh": "#result-meeting-result/race_id=2154826&track_id=7&r_date=2025-09-15&r_time=15:59"
    },
    {
      "href_gh": "#result-meeting-result/race_id=2154827&track_id=7&r_date=2025-09-15&r_time=16:18"
    },
    {
      "href_gh": "#result-meeting-result/race_id=2154828&track_id=7&r_date=2025-09-15&r_time=16:37"
    },
    {
      "href_gh": "#result-meeting-result/race_id=2154829&track_id=7&r_date=2025-09-15&r_time=16:56"
    },
    {
      "href_gh": "#result-meeting-result/race_id=2154830&track_id=7&r_date=2025-09-15&r_time=17:14"
    },
    {
      "href_gh": "#result-meeting-result/race_id=2154831&track_id=7&r_date=2025-09-15&r_time=17:29"
    },
    {
      "href_gh": "#result-meeting-result/race_id=2154832&track_id=7&r_date=2025-09-15&r_time=17:46"
    },
    {
      "href_gh": "#result-meeting-result/race_id=2154833&track_id=7&r_date=2025-09-15&r_time=17:59"
    },
    {
      "href_gh": "#result-meeting-result/race_id=2154834&track_id=7&r_date=2025-09-15&r_time=18:16"
    },
    {
      "href_gh": "#result-meeting-result/race_id=2154366&track_id=66&r_date=2025-09-15&r_time=14:33"
    },
    {
      "href_gh": "#result-meeting-result/race_id=2154367&track_id=66&r_date=2025-09-15&r_time=14:52"
    },
    {
      "href_gh": "#result-meeting-result/race_id=2154368&track_id=66&r_date=2025-09-15&r_time=15:11"
    },
    {
      "href_gh": "#result-meeting-result/race_id=2154369&track_id=66&r_date=2025-09-15&r_time=15:29"
    },
    {
      "href_gh": "#result-meeting-result/race_id=2154370&track_id=66&r_date=2025-09-15&r_time=15:49"
    },
    {
      "href_gh": "#result-meeting-result/race_id=2154371&track_id=66&r_date=2025-09-15&r_time=16:07"
    },
    {
      "href_gh": "#result-meeting-result/race_id=2154372&track_id=66&r_date=2025-09-15&r_time=16:26"
    },
    {
      "href_gh": "#result-meeting-result/race_id=2154373&track_id=66&r_date=2025-09-15&r_time=16:44"
    },
    {
      "href_gh": "#result-meeting-result/race_id=2154374&track_id=66&r_date=2025-09-15&r_time=17:03"
    },
    {
      "href_gh": "#result-meeting-result/race_id=2154375&track_id=66&r_date=2025-09-15&r_time=17:21"
    },
    {
      "href_gh": "#result-meeting-result/race_id=2154376&track_id=66&r_date=2025-09-15&r_time=17:39"
    },
    {
      "href_gh": "#result-meeting-result/race_id=2154377&track_id=66&r_date=2025-09-15&r_time=17:54"
    },
    {
      "href_gh": "#result-meeting-result/race_id=2154726&track_id=69&r_date=2025-09-15&r_time=18:11"
    },
    {
      "href_gh": "#result-meeting-result/race_id=2154727&track_id=69&r_date=2025-09-15&r_time=18:29"
    },
    {
      "href_gh": "#result-meeting-result/race_id=2154728&track_id=69&r_date=2025-09-15&r_time=18:46"
    },
    {
      "href_gh": "#result-meeting-result/race_id=2154729&track_id=69&r_date=2025-09-15&r_time=19:04"
    },
    {
      "href_gh": "#result-meeting-result/race_id=2154730&track_id=69&r_date=2025-09-15&r_time=19:24"
    },
    {
      "href_gh": "#result-meeting-result/race_id=2154731&track_id=69&r_date=2025-09-15&r_time=19:42"
    },
    {
      "href_gh": "#result-meeting-result/race_id=2154732&track_id=69&r_date=2025-09-15&r_time=19:58"
    },
    {
      "href_gh": "#result-meeting-result/race_id=2154733&track_id=69&r_date=2025-09-15&r_time=20:16"
    },
    {
      "href_gh": "#result-meeting-result/race_id=2154734&track_id=69&r_date=2025-09-15&r_time=20:34"
    },
    {
      "href_gh": "#result-meeting-result/race_id=2154735&track_id=69&r_date=2025-09-15&r_time=20:52"
    },
    {
      "href_gh": "#result-meeting-result/race_id=2154913&track_id=48&r_date=2025-09-15&r_time=20:00"
    },
    {
      "href_gh": "#result-meeting-result/race_id=2154914&track_id=48&r_date=2025-09-15&r_time=20:13"
    },
    {
      "href_gh": "#result-meeting-result/race_id=2154915&track_id=48&r_date=2025-09-15&r_time=20:26"
    },
    {
      "href_gh": "#result-meeting-result/race_id=2154916&track_id=48&r_date=2025-09-15&r_time=20:39"
    },
    {
      "href_gh": "#result-meeting-result/race_id=2154917&track_id=48&r_date=2025-09-15&r_time=20:59"
    },
    {
      "href_gh": "#result-meeting-result/race_id=2154918&track_id=48&r_date=2025-09-15&r_time=21:12"
    },
    {
      "href_gh": "#result-meeting-result/race_id=2154919&track_id=48&r_date=2025-09-15&r_time=21:25"
    },
    {
      "href_gh": "#result-meeting-result/race_id=2154920&track_id=48&r_date=2025-09-15&r_time=21:38"
    }
  ]
}