{
  "data_corrida": "2025-10-05",
  "corridas": [
    {
      "href_gh": "#result-meeting-result/race_id=2158551&track_id=16&r_date=2025-10-05&r_time=11:01"
    },
    {
      "href_gh": "#result-meeting-result/race_id=2158552&track_id=16&r_date=2025-10-05&r_time=11:18"
    },
    {
      "href_gh": "#result-meeting-result/race_id=2158553&track_id=16&r_date=2025-10-05&r_time=11:34"
    },
    {
      "href_gh": "#result-meeting-result/race_id=2158554&track_id=16&r_date=2025-10-05&r_time=11:52"
    },
    {
      "href_gh": "#result-meeting-result/race_id=2158555&track_id=16&r_date=2025-10-05&r_time=12:09"
    },
    {
      "href_gh": "#result-meeting-result/race_id=2158556&track_id=16&r_date=2025-10-05&r_time=12:26"
    },
    {
      "href_gh": "#result-meeting-result/race_id=2158557&track_id=16&r_date=2025-10-05&r_time=12:42"
    },
    {
      "href_gh": "#result-meeting-result/race_id=2158558&track_id=16&r_date=2025-10-05&r_time=12:59"
    },
    {
      "href_gh": "#result-meeting-result/race_id=2158559&track_id=16&r_date=2025-10-05&r_time=13:17"
    },
    {
      "href_gh": "#result-meeting-result/race_id=2158560&track_id=16&r_date=2025-10-05&r_time=13:33"
    },
    {
      "href_gh": "#result-meeting-result/race_id=2158561&track_id=16&r_date=2025-10-05&r_time=13:51"
    },
    {
      "href_gh": "#result-meeting-result/race_id=2158562&track_id=16&r_date=2025-10-05&r_time=14:07"
    },
    {
      "href_gh": "#result-meeting-result/race_id=2158563&track_id=61&r_date=2025-10-05&r_time=11:09"
    },
    {
      "href_gh": "#result-meeting-result/race_id=2158564&track_id=61&r_date=2025-10-05&r_time=11:27"
    },
    {
      "href_gh": "#result-meeting-result/race_id=2158565&track_id=61&r_date=2025-10-05&r_time=11:43"
    },
    {
      "href_gh": "#result-meeting-result/race_id=2158566&track_id=61&r_date=2025-10-05&r_time=12:01"
    },
    {
      "href_gh": "#result-meeting-result/race_id=2158567&track_id=61&r_date=2025-10-05&r_time=12:18"
    },
    {
      "href_gh": "#result-meeting-result/race_id=2158568&track_id=61&r_date=2025-10-05&r_time=12:34"
    },
    {
      "href_gh": "#result-meeting-result/race_id=2158569&track_id=61&r_date=2025-10-05&r_time=12:51"
    },
    {
      "href_gh": "#result-meeting-result/race_id=2158570&track_id=61&r_date=2025-10-05&r_time=13:08"
    },
    {
      "href_gh": "#result-meeting-result/race_id=2158571&track_id=61&r_date=2025-10-05&r_time=13:26"
    },
    {
      "href_gh": "#result-meeting-result/race_id=2158572&track_id=61&r_date=2025-10-05&r_time=13:42"
    },
    {
      "href_gh": "#result-meeting-result/race_id=2158573&track_id=61&r_date=2025-10-05&r_time=13:59"
    },
    {
      "href_gh": "#result-meeting-result/race_id=2158574&track_id=61&r_date=2025-10-05&r_time=14:14"
    },
    {
      "href_gh": "#result-meeting-result/race_id=2158915&track_id=5&r_date=2025-10-05&r_time=14:23"
    },
    {
      "href_gh": "#result-meeting-result/race_id=2158916&track_id=5&r_date=2025-10-05&r_time=14:41"
    },
    {
      "href_gh": "#result-meeting-result/race_id=2158917&track_id=5&r_date=2025-10-05&r_time=15:01"
    },
    {
      "href_gh": "#result-meeting-result/race_id=2158918&track_id=5&r_date=2025-10-05&r_time=15:19"
    },
    {
      "href_gh": "#result-meeting-result/race_id=2158919&track_id=5&r_date=2025-10-05&r_time=15:38"
    },
    {
      "href_gh": "#result-meeting-result/race_id=2158920&track_id=5&r_date=2025-10-05&r_time=15:57"
    },
    {
      "href_gh": "#result-meeting-result/race_id=2158921&track_id=5&r_date=2025-10-05&r_time=16:16"
    },
    {
      "href_gh": "#result-meeting-result/race_id=2158922&track_id=5&r_date=2025-10-05&r_time=16:34"
    },
    {
      "href_gh": "#result-meeting-result/race_id=2158923&track_id=5&r_date=2025-10-05&r_time=16:53"
    },
    {
      "href_gh": "#result-meeting-result/race_id=2158924&track_id=5&r_date=2025-10-05&r_time=17:12"
    },
    {
      "href_gh": "#result-meeting-result/race_id=2158925&track_id=5&r_date=2025-10-05&r_time=17:31"
    },
    {
      "href_gh": "#result-meeting-result/race_id=2158926&track_id=5&r_date=2025-10-05&r_time=17:49"
    },
    {
      "href_gh": "#result-meeting-result/race_id=2158575&track_id=34&r_date=2025-10-05&r_time=14:31"
    },
    {
      "href_gh": "#result-meeting-result/race_id=2158576&track_id=34&r_date=2025-10-05&r_time=14:49"
    },
    {
      "href_gh": "#result-meeting-result/race_id=2158577&track_id=34&r_date=2025-10-05&r_time=15:09"
    },
    {
      "href_gh": "#result-meeting-result/race_id=2158578&track_id=34&r_date=2025-10-05&r_time=15:27"
    },
    {
      "href_gh": "#result-meeting-result/race_id=2158579&track_id=34&r_date=2025-10-05&r_time=15:47"
    },
    {
      "href_gh": "#result-meeting-result/race_id=2158580&track_id=34&r_date=2025-10-05&r_time=16:04"
    },
    {
      "href_gh": "#result-meeting-result/race_id=2158581&track_id=34&r_date=2025-10-05&r_time=16:24"
    },
    {
      "href_gh": "#result-meeting-result/race_id=2158582&track_id=34&r_date=2025-10-05&r_time=16:42"
    },
    {
      "href_gh": "#result-meeting-result/race_id=2158583&track_id=34&r_date=2025-10-05&r_time=17:01"
    },
    {
      "href_gh": "#result-meeting-result/race_id=2158584&track_id=34&r_date=2025-10-05&r_time=17:19"
    },
    {
      "href_gh": "#result-meeting-result/race_id=2158585&track_id=34&r_date=2025-10-05&r_time=17:37"
    },
    {
      "href_gh": "#result-meeting-result/race_id=2158586&track_id=34&r_date=2025-10-05&r_time=17:57"
    },
    {
      "href_gh": "#result-meeting-result/race_id=2158746&track_id=76&r_date=2025-10-05&r_time=18:08"
    },
    {
      "href_gh": "#result-meeting-result/race_id=2158747&track_id=76&r_date=2025-10-05&r_time=18:26"
    },
    {
      "href_gh": "#result-meeting-result/race_id=2158748&track_id=76&r_date=2025-10-05&r_time=18:42"
    },
    {
      "href_gh": "#result-meeting-result/race_id=2158749&track_id=76&r_date=2025-10-05&r_time=18:59"
    },
    {
      "href_gh": "#result-meeting-result/race_id=2158750&track_id=76&r_date=2025-10-05&r_time=19:16"
    },
    {
      "href_gh": "#result-meeting-result/race_id=2158751&track_id=76&r_date=2025-10-05&r_time=19:33"
    },
    {
      "href_gh": "#result-meeting-result/race_id=2158752&track_id=76&r_date=2025-10-05&r_time=19:49"
    },
    {
      "href_gh": "#result-meeting-result/race_id=2158753&track_id=76&r_date=2025-10-05&r_time=20:07"
    },
    {
      "href_gh": "#result-meeting-result/race_id=2158754&track_id=76&r_date=2025-10-05&r_time=20:24"
    },
    {
      "href_gh": "#result-meeting-result/race_id=2158755&track_id=76&r_date=2025-10-05&r_time=20:41"
    },
    {
      "href_gh": "#result-meeting-result/race_id=2158756&track_id=76&r_date=2025-10-05&r_time=20:59"
    },
    {
      "href_gh": "#result-meeting-result/race_id=2158757&track_id=76&r_date=2025-10-05&r_time=21:16"
    },
    {
      "href_gh": "#result-meeting-result/race_id=2158734&track_id=66&r_date=2025-10-05&r_time=10:32"
    },
    {
      "href_gh": "#result-meeting-result/race_id=2158735&track_id=66&r_date=2025-10-05&r_time=10:48"
    },
    {
      "href_gh": "#result-meeting-result/race_id=2158736&track_id=66&r_date=2025-10-05&r_time=11:04"
    },
    {
      "href_gh": "#result-meeting-result/race_id=2158737&track_id=66&r_date=2025-10-05&r_time=11:21"
    },
    {
      "href_gh": "#result-meeting-result/race_id=2158738&track_id=66&r_date=2025-10-05&r_time=11:38"
    },
    {
      "href_gh": "#result-meeting-result/race_id=2158739&track_id=66&r_date=2025-10-05&r_time=11:54"
    },
    {
      "href_gh": "#result-meeting-result/race_id=2158740&track_id=66&r_date=2025-10-05&r_time=12:12"
    },
    {
      "href_gh": "#result-meeting-result/race_id=2158741&track_id=66&r_date=2025-10-05&r_time=12:29"
    },
    {
      "href_gh": "#result-meeting-result/race_id=2158742&track_id=66&r_date=2025-10-05&r_time=12:46"
    },
    {
      "href_gh": "#result-meeting-result/race_id=2158743&track_id=66&r_date=2025-10-05&r_time=13:03"
    },
    {
      "href_gh": "#result-meeting-result/race_id=2158744&track_id=66&r_date=2025-10-05&r_time=13:19"
    },
    {
      "href_gh": "#result-meeting-result/race_id=2158745&track_id=66&r_date=2025-10-05&r_time=13:37"
    },
    {
      "href_gh": "#result-meeting-result/race_id=2158892&track_id=73&r_date=2025-10-05&r_time=10:41"
    },
    {
      "href_gh": "#result-meeting-result/race_id=2158893&track_id=73&r_date=2025-10-05&r_time=10:57"
    },
    {
      "href_gh": "#result-meeting-result/race_id=2158894&track_id=73&r_date=2025-10-05&r_time=11:13"
    },
    {
      "href_gh": "#result-meeting-result/race_id=2158895&track_id=73&r_date=2025-10-05&r_time=11:29"
    },
    {
      "href_gh": "#result-meeting-result/race_id=2158896&track_id=73&r_date=2025-10-05&r_time=11:47"
    },
    {
      "href_gh": "#result-meeting-result/race_id=2158897&track_id=73&r_date=2025-10-05&r_time=12:04"
    },
    {
      "href_gh": "#result-meeting-result/race_id=2158898&track_id=73&r_date=2025-10-05&r_time=12:21"
    },
    {
      "href_gh": "#result-meeting-result/race_id=2158899&track_id=73&r_date=2025-10-05&r_time=12:38"
    },
    {
      "href_gh": "#result-meeting-result/race_id=2158900&track_id=73&r_date=2025-10-05&r_time=12:54"
    },
    {
      "href_gh": "#result-meeting-result/race_id=2158901&track_id=73&r_date=2025-10-05&r_time=13:12"
    },
    {
      "href_gh": "#result-meeting-result/race_id=2158902&track_id=73&r_date=2025-10-05&r_time=13:29"
    },
    {
      "href_gh": "#result-meeting-result/race_id=2158903&track_id=73&r_date=2025-10-05&r_time=13:47"
    },
    {
      "href_gh": "#result-meeting-result/race_id=2158904&track_id=73&r_date=2025-10-05&r_time=14:03"
    },
    {
      "href_gh": "#result-meeting-result/race_id=2158905&track_id=73&r_date=2025-10-05&r_time=14:18"
    },
    {
      "href_gh": "#result-meeting-result/race_id=2158906&track_id=73&r_date=2025-10-05&r_time=14:36"
    },
    {
      "href_gh": "#result-meeting-result/race_id=2158866&track_id=7&r_date=2025-10-05&r_time=13:57"
    },
    {
      "href_gh": "#result-meeting-result/race_id=2158867&track_id=7&r_date=2025-10-05&r_time=14:16"
    },
    {
      "href_gh": "#result-meeting-result/race_id=2158868&track_id=7&r_date=2025-10-05&r_time=14:33"
    },
    {
      "href_gh": "#result-meeting-result/race_id=2158869&track_id=7&r_date=2025-10-05&r_time=14:52"
    },
    {
      "href_gh": "#result-meeting-result/race_id=2158870&track_id=7&r_date=2025-10-05&r_time=15:11"
    },
    {
      "href_gh": "#result-meeting-result/race_id=2158871&track_id=7&r_date=2025-10-05&r_time=15:29"
    },
    {
      "href_gh": "#result-meeting-result/race_id=2158872&track_id=7&r_date=2025-10-05&r_time=15:49"
    },
    {
      "href_gh": "#result-meeting-result/race_id=2158873&track_id=7&r_date=2025-10-05&r_time=16:07"
    },
    {
      "href_gh": "#result-meeting-result/race_id=2158874&track_id=7&r_date=2025-10-05&r_time=16:26"
    },
    {
      "href_gh": "#result-meeting-result/race_id=2158875&track_id=7&r_date=2025-10-05&r_time=16:44"
    },
    {
      "href_gh": "#result-meeting-result/race_id=2158876&track_id=7&r_date=2025-10-05&r_time=17:03"
    },
    {
      "href_gh": "#result-meeting-result/race_id=2158877&track_id=7&r_date=2025-10-05&r_time=17:21"
    },
    {
      "href_gh": "#result-meeting-result/race_id=2158878&track_id=7&r_date=2025-10-05&r_time=17:39"
    },
    {
      "href_gh": "#result-meeting-result/race_id=2158879&track_id=7&r_date=2025-10-05&r_time=17:54"
    },
    {
      "href_gh": "#result-meeting-result/race_id=2158702&track_id=53&r_date=2025-10-05&r_time=14:26"
    },
    {
      "href_gh": "#result-meeting-result/race_id=2158703&track_id=53&r_date=2025-10-05&r_time=14:44"
    },
    {
      "href_gh": "#result-meeting-result/race_id=2158704&track_id=53&r_date=2025-10-05&r_time=15:03"
    },
    {
      "href_gh": "#result-meeting-result/race_id=2158705&track_id=53&r_date=2025-10-05&r_time=15:22"
    },
    {
      "href_gh": "#result-meeting-result/race_id=2158706&track_id=53&r_date=2025-10-05&r_time=15:41"
    },
    {
      "href_gh": "#result-meeting-result/race_id=2158707&track_id=53&r_date=2025-10-05&r_time=15:59"
    },
    {
      "href_gh": "#result-meeting-result/race_id=2158708&track_id=53&r_date=2025-10-05&r_time=16:18"
    },
    {
      "href_gh": "#result-meeting-result/race_id=2158709&track_id=53&r_date=2025-10-05&r_time=16:37"
    },
    {
      "href_gh": "#result-meeting-result/race_id=2158710&track_id=53&r_date=2025-10-05&r_time=16:56"
    },
    {
      "href_gh": "#result-meeting-result/race_id=2158711&track_id=53&r_date=2025-10-05&r_time=17:14"
    },
    {
      "href_gh": "#result-meeting-result/race_id=2158689&track_id=51&r_date=2025-10-05&r_time=18:01"
    },
    {
      "href_gh": "#result-meeting-result/race_id=2158690&track_id=51&r_date=2025-10-05&r_time=18:19"
    },
    {
      "href_gh": "#result-meeting-result/race_id=2158691&track_id=51&r_date=2025-10-05&r_time=18:36"
    },
    {
      "href_gh": "#result-meeting-result/race_id=2158692&track_id=51&r_date=2025-10-05&r_time=18:52"
    },
    {
      "href_gh": "#result-meeting-result/race_id=2158693&track_id=51&r_date=2025-10-05&r_time=19:10"
    },
    {
      "href_gh": "#result-meeting-result/race_id=2158694&track_id=51&r_date=2025-10-05&r_time=19:28"
    },
    {
      "href_gh": "#result-meeting-result/race_id=2158695&track_id=51&r_date=2025-10-05&r_time=19:46"
    },
    {
      "href_gh": "#result-meeting-result/race_id=2158696&track_id=51&r_date=2025-10-05&r_time=20:04"
    },
    {
      "href_gh": "#result-meeting-result/race_id=2158697&track_id=51&r_date=2025-10-05&r_time=20:21"
    },
    {
      "href_gh": "#result-meeting-result/race_id=2158698&track_id=51&r_date=2025-10-05&r_time=20:38"
    },
    {
      "href_gh": "#result-meeting-result/race_id=2158699&track_id=51&r_date=2025-10-05&r_time=20:56"
    },
    {
      "href_gh": "#result-meeting-result/race_id=2158700&track_id=51&r_date=2025-10-05&r_time=21:12"
    },
    {
      "href_gh": "#result-meeting-result/race_id=2158392&track_id=41&r_date=2025-10-05&r_time=18:04"
    },
    {
      "href_gh": "#result-meeting-result/race_id=2158393&track_id=41&r_date=2025-10-05&r_time=18:21"
    },
    {
      "href_gh": "#result-meeting-result/race_id=2158394&track_id=41&r_date=2025-10-05&r_time=18:39"
    },
    {
      "href_gh": "#result-meeting-result/race_id=2158395&track_id=41&r_date=2025-10-05&r_time=18:56"
    },
    {
      "href_gh": "#result-meeting-result/race_id=2158396&track_id=41&r_date=2025-10-05&r_time=19:14"
    },
    {
      "href_gh": "#result-meeting-result/race_id=2158397&track_id=41&r_date=2025-10-05&r_time=19:31"
    },
    {
      "href_gh": "#result-meeting-result/race_id=2158398&track_id=41&r_date=2025-10-05&r_time=19:51"
    },
    {
      "href_gh": "#result-meeting-result/race_id=2158399&track_id=41&r_date=2025-10-05&r_time=20:09"
    },
    {
      "href_gh": "#result-meeting-result/race_id=2158400&track_id=41&r_date=2025-10-05&r_time=20:26"
    },
    {
      "href_gh": "#result-meeting-result/race_id=2158401&track_id=41&r_date=2025-10-05&r_time=20:43"
    },
    {
      "href_gh": "#result-meeting-result/race_id=2158402&track_id=41&r_date=2025-10-05&r_time=21:01"
    },
    {
      "href_gh": "#result-meeting-result/race_id=2158403&track_id=41&r_date=2025-10-05&r_time=21:18"
    },
    {
      "href_gh": "#result-meeting-result/race_id=2158587&track_id=86&r_date=2025-10-05&r_time=18:11"
    },
    {
      "href_gh": "#result-meeting-result/race_id=2158588&track_id=86&r_date=2025-10-05&r_time=18:29"
    },
    {
      "href_gh": "#result-meeting-result/race_id=2158589&track_id=86&r_date=2025-10-05&r_time=18:46"
    },
    {
      "href_gh": "#result-meeting-result/race_id=2158590&track_id=86&r_date=2025-10-05&r_time=19:04"
    },
    {
      "href_gh": "#result-meeting-result/race_id=2158591&track_id=86&r_date=2025-10-05&r_time=19:24"
    },
    {
      "href_gh": "#result-meeting-result/race_id=2158592&track_id=86&r_date=2025-10-05&r_time=19:42"
    },
    {
      "href_gh": "#result-meeting-result/race_id=2158593&track_id=86&r_date=2025-10-05&r_time=19:58"
    },
    {
      "href_gh": "#result-meeting-result/race_id=2158594&track_id=86&r_date=2025-10-05&r_time=20:16"
    }
  ]
}